{
  "collapse-filter": false,
  "search": "",
  "showTags": true,
  "showAttachments": true,
  "hideUnresolved": false,
  "showOrphans": true,
  "collapse-color-groups": false,
  "colorGroups": [],
  "collapse-display": false,
  "showArrow": true,
  "textFadeMultiplier": 0.1,
  "nodeSizeMultiplier": 2.49704427083333,
  "lineSizeMultiplier": 1.30692274305556,
  "collapse-forces": false,
  "centerStrength": 0,
  "repelStrength": 20,
  "linkStrength": 1,
  "linkDistance": 500,
  "scale": 0.01852288088119168,
  "close": false
}